setup.py
dist_allocations/Binomialdistribution.py
dist_allocations/Gaussiandistribution.py
dist_allocations/Generaldistribution.py
dist_allocations/__init__.py
dist_allocations.egg-info/PKG-INFO
dist_allocations.egg-info/SOURCES.txt
dist_allocations.egg-info/dependency_links.txt
dist_allocations.egg-info/not-zip-safe
dist_allocations.egg-info/top_level.txt