Metadata-Version: 1.0
Name: dist-allocations
Version: 0.1
Summary: Gaussian distributions
Home-page: UNKNOWN
Author: Charles Arnold
Author-email: kingme@email.com
License: UNKNOWN
Platform: UNKNOWN
